YehuoStm32KuKaifaShizhanZhinanFix1/README.md
YehuoStm32KuKaifaShizhanZhinanFix1/__init__.py
YehuoStm32KuKaifaShizhanZhinanFix1/__main__.py
YehuoStm32KuKaifaShizhanZhinanFix1/file.epub
YehuoStm32KuKaifaShizhanZhinanFix1/index.html
YehuoStm32KuKaifaShizhanZhinanFix1/css/__init__.py
YehuoStm32KuKaifaShizhanZhinanFix1/css/annotations.css
YehuoStm32KuKaifaShizhanZhinanFix1/css/main.css
YehuoStm32KuKaifaShizhanZhinanFix1/css/normalize.css
YehuoStm32KuKaifaShizhanZhinanFix1/css/popup.css
YehuoStm32KuKaifaShizhanZhinanFix1/font/__init__.py
YehuoStm32KuKaifaShizhanZhinanFix1/font/fontello.eot
YehuoStm32KuKaifaShizhanZhinanFix1/font/fontello.svg
YehuoStm32KuKaifaShizhanZhinanFix1/font/fontello.ttf
YehuoStm32KuKaifaShizhanZhinanFix1/font/fontello.woff
YehuoStm32KuKaifaShizhanZhinanFix1/img/__init__.py
YehuoStm32KuKaifaShizhanZhinanFix1/img/annotator-glyph-sprite.png
YehuoStm32KuKaifaShizhanZhinanFix1/img/annotator-icon-sprite.png
YehuoStm32KuKaifaShizhanZhinanFix1/img/apple-touch-icon.png
YehuoStm32KuKaifaShizhanZhinanFix1/img/cancelfullscreen.png
YehuoStm32KuKaifaShizhanZhinanFix1/img/close.png
YehuoStm32KuKaifaShizhanZhinanFix1/img/fullscreen.png
YehuoStm32KuKaifaShizhanZhinanFix1/img/loader.gif
YehuoStm32KuKaifaShizhanZhinanFix1/img/menu-icon.png
YehuoStm32KuKaifaShizhanZhinanFix1/img/save.png
YehuoStm32KuKaifaShizhanZhinanFix1/img/saved.png
YehuoStm32KuKaifaShizhanZhinanFix1/img/settings-s.png
YehuoStm32KuKaifaShizhanZhinanFix1/img/settings.png
YehuoStm32KuKaifaShizhanZhinanFix1/img/star.png
YehuoStm32KuKaifaShizhanZhinanFix1/js/__init__.py
YehuoStm32KuKaifaShizhanZhinanFix1/js/epub.js
YehuoStm32KuKaifaShizhanZhinanFix1/js/epub.min.js
YehuoStm32KuKaifaShizhanZhinanFix1/js/epub.min.map
YehuoStm32KuKaifaShizhanZhinanFix1/js/hooks.min.js
YehuoStm32KuKaifaShizhanZhinanFix1/js/hooks.min.map
YehuoStm32KuKaifaShizhanZhinanFix1/js/reader.js
YehuoStm32KuKaifaShizhanZhinanFix1/js/reader.js.map
YehuoStm32KuKaifaShizhanZhinanFix1/js/reader.min.js
yehuo_stm32_ku_kaifa_shizhan_zhinan_fix1-2025.3.24.0.dist-info/METADATA
yehuo_stm32_ku_kaifa_shizhan_zhinan_fix1-2025.3.24.0.dist-info/WHEEL
yehuo_stm32_ku_kaifa_shizhan_zhinan_fix1-2025.3.24.0.dist-info/entry_points.txt
yehuo_stm32_ku_kaifa_shizhan_zhinan_fix1-2025.3.24.0.dist-info/top_level.txt
yehuo_stm32_ku_kaifa_shizhan_zhinan_fix1-2025.3.24.0.dist-info/RECORD
